Metadata-Version: 1.1
Name: qcache
Version: 0.9.3
Summary: In memory cache server with analytical query capabilities
Home-page: https://github.com/tobgu/qcache
Author: Tobias Gustafsson
Author-email: tobias.l.gustafsson@gmail.com
License: MIT
Keywords: qcache
Platform: UNKNOWN
Classifier: Development Status :: 4 - Beta
Classifier: Intended Audience :: Developers
Classifier: License :: OSI Approved :: MIT License
Classifier: Natural Language :: English
Classifier: Programming Language :: Python :: 2
Classifier: Programming Language :: Python :: 2.7
Classifier: Programming Language :: Python :: Implementation :: CPython
